wxpal_cli/__init__.py
wxpal_cli/cli.py
wxpal_cli/s3_handler.py
wxpal-0.1.0.dist-info/METADATA
wxpal-0.1.0.dist-info/WHEEL
wxpal-0.1.0.dist-info/entry_points.txt
wxpal-0.1.0.dist-info/top_level.txt
wxpal-0.1.0.dist-info/RECORD
