Metadata-Version: 2.1
Name: wxpal
Version: 0.1.0
Requires-Dist: boto3
